bloodymary/__init__.py
bloodymary/constants.py
bloodymary/exceptions.py
bloodymary/formats/__init__.py
bloodymary/formats/base.py
bloodymary/formats/ios_blood_pressure.py
bloodymary/formats/loader.py
bloodymary/measurement.py
bloodymary-0.2.dist-info/WHEEL
bloodymary-0.2.dist-info/METADATA
bloodymary-0.2.dist-info/RECORD
