Metadata-Version: 2.1
Name: bloodymary
Version: 0.2
Summary: Utility for parsing and processing blood pressure measurements
License: PSF
Author: Ilkka Tuohela
Author-email: hile@iki.fi
Requires-Python: >=3.9,<4.0
Classifier: License :: Other/Proprietary License
Classifier: Programming Language :: Python :: 3
Classifier: Programming Language :: Python :: 3.10
Classifier: Programming Language :: Python :: 3.9
Requires-Dist: cli-toolkit (>=2.1.5,<3.0.0)
Requires-Dist: pandas (>=1.4.3,<2.0.0)
